Metadata-Version: 1.1
Name: djangocms-table-changer
Version: 1.3.0
Summary: Table Plugin for django CMS, fork from divio with python 3 and django 1.7 migrations support
Home-page: https://github.com/changer/djangocms-table
Author: Jos van Velzen
Author-email: support
License: LICENSE.txt
Platform: OS Independent
Classifier: Development Status :: 5 - Production/Stable
Classifier: Environment :: Web Environment
Classifier: Framework :: Django
Classifier: Intended Audience :: Developers
Classifier: License :: OSI Approved :: BSD License
Classifier: Operating System :: OS Independent
Classifier: Programming Language :: Python
Classifier: Topic :: Communications
Classifier: Topic :: Internet :: WWW/HTTP :: Dynamic Content
Classifier: Topic :: Internet :: WWW/HTTP :: Dynamic Content :: Message Boards
Classifier: Programming Language :: Python :: 2.7
Classifier: Programming Language :: Python :: 3.4
